sqlpile/__init__.py
sqlpile/abcs.py
sqlpile/config.py
sqlpile/core.py
sqlpile/database.py
sqlpile/main.py
sqlpile/utils.py
sqlpile-0.3.2.dist-info/METADATA
sqlpile-0.3.2.dist-info/WHEEL
sqlpile-0.3.2.dist-info/RECORD
