Metadata-Version: 2.3
Name: sqlpile
Version: 0.3.2
Summary: Add your description here
Author-email: Kevin Hill <kivo360@gmail.com>
Requires-Python: >=3.8
Requires-Dist: aiosqlite>=0.20.0
Requires-Dist: asyncer>=0.0.7
Requires-Dist: cloudpickle>=3.0.0
Requires-Dist: cytoolz>=0.12.3
Requires-Dist: devtools>=0.12.2
Requires-Dist: diskcache>=5.6.3
Requires-Dist: duckdb-engine>=0.12.0
Requires-Dist: duckdb>=0.10.2
Requires-Dist: lancedb>=0.6.11
Requires-Dist: loguru>=0.7.2
Requires-Dist: lz4>=4.3.3
Requires-Dist: psycopg[binary]>=3.1.18
Requires-Dist: pydantic-settings>=2.2.1
Requires-Dist: pyrsistent>=0.20.0
Requires-Dist: rich>=13.7.1
Requires-Dist: sqlalchemy>=2.0.29
Requires-Dist: supamodel>=0.5.8
Requires-Dist: toolz>=0.12.1
Requires-Dist: xxhash>=3.4.1
